rjv_anywidget/__init__.py
rjv_anywidget/widget.py
rjv_anywidget/static/widget.css
rjv_anywidget/static/widget.js
json_view_anywidget-0.1.1.dist-info/METADATA
json_view_anywidget-0.1.1.dist-info/WHEEL
json_view_anywidget-0.1.1.dist-info/RECORD
