Metadata-Version: 2.4
Name: json-view-anywidget
Version: 0.1.1
Summary: Interactive JSON viewer widget for Jupyter notebooks using React JSON View
Project-URL: Homepage, https://github.com/bigeagle/anywidget-react-json-view
Project-URL: Repository, https://github.com/bigeagle/anywidget-react-json-view
Project-URL: Issues, https://github.com/bigeagle/anywidget-react-json-view/issues
Author-email: Justin Wong <justin.w.xd@gmail.com>
License: MIT
Keywords: anywidget,json,jupyter,notebook,react,widget
Requires-Python: >=3.7
Requires-Dist: anywidget>=0.9.0
